studybuddy/__init__.py
studybuddy/cli.py
studybuddy/core.py
studybuddy_teamcedar-0.8.0.dist-info/licenses/LICENSE
studybuddy_teamcedar-0.8.0.dist-info/METADATA
studybuddy_teamcedar-0.8.0.dist-info/WHEEL
studybuddy_teamcedar-0.8.0.dist-info/entry_points.txt
studybuddy_teamcedar-0.8.0.dist-info/top_level.txt
studybuddy_teamcedar-0.8.0.dist-info/RECORD
