Metadata-Version: 2.4
Name: studybuddy_teamcedar
Version: 0.8.0
Summary: A lighthearted Python package for funny study tips, excuses, and motivation.
Author: Team Cedar
License: MIT
Requires-Python: >=3.10
License-File: LICENSE
Dynamic: license-file
